apipulse/__init__.py
apipulse/core.py
apipulse-0.1.0.dist-info/LICENSE
apipulse-0.1.0.dist-info/METADATA
apipulse-0.1.0.dist-info/WHEEL
apipulse-0.1.0.dist-info/top_level.txt
apipulse-0.1.0.dist-info/RECORD
