Metadata-Version: 2.1
Name: apipulse
Version: 0.1.0
Summary: Universal test framework to test REST API
Home-page: https://github.com/quillcraftsman/apipulse
Author: quillcraftsman
Author-email: quill@craftsman.lol
License: MIT
Keywords: test,api,framework,rest
Requires-Python: >=3
License-File: LICENSE
